LICENSE.txt
MANIFEST.in
README.rst
setup.py
tryfer/__init__.py
tryfer/formatters.py
tryfer/http.py
tryfer/interfaces.py
tryfer/log.py
tryfer/trace.py
tryfer/tracers.py
tryfer.egg-info/PKG-INFO
tryfer.egg-info/SOURCES.txt
tryfer.egg-info/dependency_links.txt
tryfer.egg-info/requires.txt
tryfer.egg-info/top_level.txt
tryfer/_thrift/__init__.py
tryfer/_thrift/zipkinCore.thrift
tryfer/_thrift/zipkinCore/__init__.py
tryfer/_thrift/zipkinCore/constants.py
tryfer/_thrift/zipkinCore/ttypes.py
tryfer/tests/__init__.py
tryfer/tests/test_http.py
tryfer/tests/test_log.py
tryfer/tests/test_trace.py
tryfer/tests/test_tracers.py